LICENSE
README.md
setup.py
tastier.egg-info/PKG-INFO
tastier.egg-info/SOURCES.txt
tastier.egg-info/dependency_links.txt
tastier.egg-info/top_level.txt
tasty/CellComponent.py
tasty/Corpus.py
tasty/__init__.py
tasty/util/__init__.py
tasty/util/operator.py
tasty/util/string.py