Metadata-Version: 2.1
Name: tastier
Version: 0.1.0
Summary: A human-readable format for nested data serialization
Home-page: https://github.com/zeionara/tasty
Author: Zeio Nara
Author-email: zeionara@gmail.com
Classifier: Programming Language :: Python :: 3.10
License-File: LICENSE
